shapeless_serializers/__init__.py
shapeless_serializers/exceptions.py
shapeless_serializers/mixins.py
shapeless_serializers/serializers.py
shapeless_serializers/utils.py
drf_shapeless_serializers-1.0.5.dist-info/METADATA
drf_shapeless_serializers-1.0.5.dist-info/WHEEL
drf_shapeless_serializers-1.0.5.dist-info/top_level.txt
drf_shapeless_serializers-1.0.5.dist-info/RECORD
