Metadata-Version: 2.4
Name: drf-shapeless-serializers
Version: 1.0.5
Summary: Dynamic serializer configuration for Django REST Framework - Shape your API responses at runtime.drf-shapeless-serializers revolutionizes API development by giving you runtime serializer superpowers. Instead of creating multiple serializer classes , configure everything on the fly with one serializer to rule them all.Now you can shape your serializers like Lego cubes - rearranging fields, nesting relationships, and transforming outputs dynamically with unlimited flexibility.
Author-email: Khaled Sukkar <khaled.sukkar.contact@gmail.com>
License: MIT
Project-URL: Homepage, https://github.com/khaledsukkar2/drf-shapeless-serializers
Keywords: django,django-rest-framework,drf,serializers,api,dynamic,runtime,configuration,nested,relationships,rest,json,APIs
Classifier: Development Status :: 4 - Beta
Classifier: Environment :: Web Environment
Classifier: Framework :: Django
Classifier: Framework :: Django :: 3.2
Classifier: Framework :: Django :: 4.0
Classifier: Framework :: Django :: 4.1
Classifier: Framework :: Django :: 4.2
Classifier: Framework :: Django :: 5.0
Classifier: Framework :: Django :: 5.1
Classifier: Framework :: Django :: 5.2
Classifier: Intended Audience :: Developers
Classifier: License :: OSI Approved :: MIT License
Classifier: Operating System :: OS Independent
Classifier: Programming Language :: Python
Classifier: Programming Language :: Python :: 3
Classifier: Programming Language :: Python :: 3.8
Classifier: Programming Language :: Python :: 3.9
Classifier: Programming Language :: Python :: 3.10
Classifier: Programming Language :: Python :: 3.11
Classifier: Programming Language :: Python :: 3.12
Classifier: Programming Language :: Python :: 3.13
Classifier: Topic :: Internet :: WWW/HTTP
Classifier: Topic :: Software Development :: Libraries :: Python Modules
Classifier: Topic :: Software Development :: Libraries :: Application Frameworks
Requires-Python: >=3.8
Requires-Dist: Django>=3.2
Requires-Dist: djangorestframework>=3.12
